[
 {
  "default_value": null,
  "doc_type": "Supplier",
  "docstatus": 0,
  "doctype": "Property Setter",
  "doctype_or_field": "DocType",
  "field_name": null,
  "is_system_generated": 0,
  "modified": "2024-04-17 23:44:35.768322",
  "module": "Akwad Frappe Fixes",
  "name": "Supplier-main-track_changes",
  "property": "track_changes",
  "property_type": "Check",
  "row_name": null,
  "value": "0"
 },
 {
  "default_value": null,
  "doc_type": "User Type",
  "docstatus": 0,
  "doctype": "Property Setter",
  "doctype_or_field": "DocField",
  "field_name": "is_standard",
  "is_system_generated": 0,
  "modified": "2024-03-21 17:00:15.753102",
  "module": "Akwad Frappe Fixes",
  "name": "User Type-is_standard-read_only_depends_on",
  "property": "read_only_depends_on",
  "property_type": "Text",
  "row_name": null,
  "value": ""
 },
 {
  "default_value": null,
  "doc_type": "User",
  "docstatus": 0,
  "doctype": "Property Setter",
  "doctype_or_field": "DocField",
  "field_name": "mute_sounds",
  "is_system_generated": 0,
  "modified": "2024-02-29 13:39:30.626238",
  "module": "Akwad Frappe Fixes",
  "name": "User-mute_sounds-permlevel",
  "property": "permlevel",
  "property_type": "Int",
  "row_name": null,
  "value": "1"
 },
 {
  "default_value": null,
  "doc_type": "User",
  "docstatus": 0,
  "doctype": "Property Setter",
  "doctype_or_field": "DocField",
  "field_name": "desk_theme",
  "is_system_generated": 0,
  "modified": "2024-02-29 13:39:42.558789",
  "module": "Akwad Frappe Fixes",
  "name": "User-desk_theme-permlevel",
  "property": "permlevel",
  "property_type": "Int",
  "row_name": null,
  "value": "1"
 },
 {
  "default_value": null,
  "doc_type": "User",
  "docstatus": 0,
  "doctype": "Property Setter",
  "doctype_or_field": "DocField",
  "field_name": "banner_image",
  "is_system_generated": 0,
  "modified": "2024-02-29 13:39:54.081802",
  "module": "Akwad Frappe Fixes",
  "name": "User-banner_image-permlevel",
  "property": "permlevel",
  "property_type": "Int",
  "row_name": null,
  "value": "1"
 },
 {
  "default_value": null,
  "doc_type": "User",
  "docstatus": 0,
  "doctype": "Property Setter",
  "doctype_or_field": "DocField",
  "field_name": "change_password",
  "is_system_generated": 0,
  "modified": "2024-02-29 13:40:42.813633",
  "module": "Akwad Frappe Fixes",
  "name": "User-change_password-collapsible",
  "property": "collapsible",
  "property_type": "Check",
  "row_name": null,
  "value": "0"
 },
 {
  "default_value": null,
  "doc_type": "User",
  "docstatus": 0,
  "doctype": "Property Setter",
  "doctype_or_field": "DocField",
  "field_name": "document_follow_notify",
  "is_system_generated": 0,
  "modified": "2024-02-29 13:41:14.412836",
  "module": "Akwad Frappe Fixes",
  "name": "User-document_follow_notify-permlevel",
  "property": "permlevel",
  "property_type": "Int",
  "row_name": null,
  "value": "1"
 },
 {
  "default_value": null,
  "doc_type": "User",
  "docstatus": 0,
  "doctype": "Property Setter",
  "doctype_or_field": "DocField",
  "field_name": "email_signature",
  "is_system_generated": 0,
  "modified": "2024-02-29 13:41:26.420211",
  "module": "Akwad Frappe Fixes",
  "name": "User-email_signature-permlevel",
  "property": "permlevel",
  "property_type": "Int",
  "row_name": null,
  "value": "1"
 },
 {
  "default_value": null,
  "doc_type": "User",
  "docstatus": 0,
  "doctype": "Property Setter",
  "doctype_or_field": "DocField",
  "field_name": "thread_notify",
  "is_system_generated": 0,
  "modified": "2024-02-29 13:41:43.682428",
  "module": "Akwad Frappe Fixes",
  "name": "User-thread_notify-permlevel",
  "property": "permlevel",
  "property_type": "Int",
  "row_name": null,
  "value": "1"
 },
 {
  "default_value": null,
  "doc_type": "User",
  "docstatus": 0,
  "doctype": "Property Setter",
  "doctype_or_field": "DocField",
  "field_name": "send_me_a_copy",
  "is_system_generated": 0,
  "modified": "2024-02-29 13:41:51.503754",
  "module": "Akwad Frappe Fixes",
  "name": "User-send_me_a_copy-permlevel",
  "property": "permlevel",
  "property_type": "Int",
  "row_name": null,
  "value": "1"
 },
 {
  "default_value": null,
  "doc_type": "User",
  "docstatus": 0,
  "doctype": "Property Setter",
  "doctype_or_field": "DocField",
  "field_name": "allowed_in_mentions",
  "is_system_generated": 0,
  "modified": "2024-02-29 13:42:09.162876",
  "module": "Akwad Frappe Fixes",
  "name": "User-allowed_in_mentions-permlevel",
  "property": "permlevel",
  "property_type": "Int",
  "row_name": null,
  "value": "1"
 },
 {
  "default_value": null,
  "doc_type": "User",
  "docstatus": 0,
  "doctype": "Property Setter",
  "doctype_or_field": "DocField",
  "field_name": "simultaneous_sessions",
  "is_system_generated": 0,
  "modified": "2024-02-29 13:42:36.267119",
  "module": "Akwad Frappe Fixes",
  "name": "User-simultaneous_sessions-permlevel",
  "property": "permlevel",
  "property_type": "Int",
  "row_name": null,
  "value": "1"
 },
 {
  "default_value": null,
  "doc_type": "User",
  "docstatus": 0,
  "doctype": "Property Setter",
  "doctype_or_field": "DocField",
  "field_name": "social_logins",
  "is_system_generated": 0,
  "modified": "2024-02-29 13:42:46.369943",
  "module": "Akwad Frappe Fixes",
  "name": "User-social_logins-permlevel",
  "property": "permlevel",
  "property_type": "Int",
  "row_name": null,
  "value": "1"
 },
 {
  "default_value": null,
  "doc_type": "User",
  "docstatus": 0,
  "doctype": "Property Setter",
  "doctype_or_field": "DocField",
  "field_name": "sb3",
  "is_system_generated": 0,
  "modified": "2024-02-29 13:43:49.675191",
  "module": "Akwad Frappe Fixes",
  "name": "User-security_settings-permlevel",
  "property": "collapsible",
  "property_type": "Check",
  "row_name": null,
  "value": "0"
 },
 {
  "default_value": null,
  "doc_type": "User",
  "docstatus": 0,
  "doctype": "Property Setter",
  "doctype_or_field": "DocField",
  "field_name": "connections_tab",
  "is_system_generated": 0,
  "modified": "2024-02-29 13:44:44.426648",
  "module": "Akwad Frappe Fixes",
  "name": "User-connections_tab-hidden",
  "property": "hidden",
  "property_type": "Check",
  "row_name": null,
  "value": "1"
 },
 {
  "default_value": null,
  "doc_type": "User",
  "docstatus": 0,
  "doctype": "Property Setter",
  "doctype_or_field": "DocField",
  "field_name": "user_type",
  "is_system_generated": 0,
  "modified": "2024-02-29 13:47:57.195647",
  "module": "Akwad Frappe Fixes",
  "name": "User-user_type-permlevel",
  "property": "permlevel",
  "property_type": "Int",
  "row_name": null,
  "value": "0"
 },
 {
  "default_value": null,
  "doc_type": "User",
  "docstatus": 0,
  "doctype": "Property Setter",
  "doctype_or_field": "DocField",
  "field_name": "role_profile_name",
  "is_system_generated": 0,
  "modified": "2024-02-29 14:19:27.730382",
  "module": "Akwad Frappe Fixes",
  "name": "User-role_profile_name-permlevel",
  "property": "permlevel",
  "property_type": "Int",
  "row_name": null,
  "value": "1"
 },
 {
  "default_value": null,
  "doc_type": "User",
  "docstatus": 0,
  "doctype": "Property Setter",
  "doctype_or_field": "DocField",
  "field_name": "roles_html",
  "is_system_generated": 0,
  "modified": "2024-02-29 13:49:39.297259",
  "module": "Akwad Frappe Fixes",
  "name": "User-roles_html-permlevel",
  "property": "permlevel",
  "property_type": "Int",
  "row_name": null,
  "value": "1"
 },
 {
  "default_value": null,
  "doc_type": "User",
  "docstatus": 0,
  "doctype": "Property Setter",
  "doctype_or_field": "DocField",
  "field_name": "module_profile",
  "is_system_generated": 0,
  "modified": "2024-02-29 14:12:26.870974",
  "module": "Akwad Frappe Fixes",
  "name": "User-module_profile-permlevel",
  "property": "permlevel",
  "property_type": "Int",
  "row_name": null,
  "value": "1"
 },
 {
  "default_value": null,
  "doc_type": "User",
  "docstatus": 0,
  "doctype": "Property Setter",
  "doctype_or_field": "DocField",
  "field_name": "enabled",
  "is_system_generated": 0,
  "modified": "2024-02-29 14:23:35.936254",
  "module": "Akwad Frappe Fixes",
  "name": "User-enabled-read_only",
  "property": "read_only",
  "property_type": "Check",
  "row_name": null,
  "value": "0"
 },
 {
  "default_value": null,
  "doc_type": "User Type",
  "docstatus": 0,
  "doctype": "Property Setter",
  "doctype_or_field": "DocField",
  "field_name": "is_standard",
  "is_system_generated": 0,
  "modified": "2024-02-29 14:41:46.421458",
  "module": "Akwad Frappe Fixes",
  "name": "User Type-is_standard-depends_on",
  "property": "depends_on",
  "property_type": "Text",
  "row_name": null,
  "value": null
 },
 {
  "default_value": null,
  "doc_type": "Customer",
  "docstatus": 0,
  "doctype": "Property Setter",
  "doctype_or_field": "DocType",
  "field_name": null,
  "is_system_generated": 0,
  "modified": "2024-02-29 15:52:18.474494",
  "module": "Akwad Frappe Fixes",
  "name": "Customer-main-track_changes",
  "property": "track_changes",
  "property_type": "Check",
  "row_name": null,
  "value": "0"
 },
 {
  "default_value": null,
  "doc_type": "Serial No",
  "docstatus": 0,
  "doctype": "Property Setter",
  "doctype_or_field": "DocType",
  "field_name": null,
  "is_system_generated": 0,
  "modified": "2024-02-29 15:52:32.482600",
  "module": "Akwad Frappe Fixes",
  "name": "Serial No-main-track_changes",
  "property": "track_changes",
  "property_type": "Check",
  "row_name": null,
  "value": "0"
 },
 {
  "default_value": null,
  "doc_type": "Workspace",
  "docstatus": 0,
  "doctype": "Property Setter",
  "doctype_or_field": "DocField",
  "field_name": "module",
  "is_system_generated": 0,
  "modified": "2024-02-25 17:15:21.396800",
  "module": "Akwad Frappe Fixes",
  "name": "Workspace-module-hidden",
  "property": "read_only",
  "property_type": "Check",
  "row_name": null,
  "value": "0"
 },
 {
  "default_value": null,
  "doc_type": "User Type",
  "docstatus": 0,
  "doctype": "Property Setter",
  "doctype_or_field": "DocField",
  "field_name": "apply_user_permission_on",
  "is_system_generated": 0,
  "modified": "2024-01-06 18:13:42.930089",
  "module": "Akwad Frappe Fixes",
  "name": "User Type-apply_user_permission_on-mandatory_depends_on",
  "property": "mandatory_depends_on",
  "property_type": "Data",
  "row_name": null,
  "value": ""
 },
 {
  "default_value": null,
  "doc_type": "User Type",
  "docstatus": 0,
  "doctype": "Property Setter",
  "doctype_or_field": "DocField",
  "field_name": "user_id_field",
  "is_system_generated": 0,
  "modified": "2024-01-06 18:13:31.153914",
  "module": "Akwad Frappe Fixes",
  "name": "User Type-user_id_field-mandatory_depends_on",
  "property": "mandatory_depends_on",
  "property_type": "Data",
  "row_name": null,
  "value": ""
 },
 {
  "default_value": null,
  "doc_type": "Translation",
  "docstatus": 0,
  "doctype": "Property Setter",
  "doctype_or_field": "DocType",
  "field_name": null,
  "is_system_generated": 0,
  "modified": "2023-12-23 16:15:26.559150",
  "module": "Akwad Frappe Fixes",
  "name": "Translation-main-track_changes",
  "property": "track_changes",
  "property_type": "Check",
  "row_name": null,
  "value": "0"
 },
 {
  "default_value": null,
  "doc_type": "User",
  "docstatus": 0,
  "doctype": "Property Setter",
  "doctype_or_field": "DocType",
  "field_name": null,
  "is_system_generated": 0,
  "modified": "2024-01-03 16:59:52.412395",
  "module": "Akwad Frappe Fixes",
  "name": "User-main-track_changes",
  "property": "track_changes",
  "property_type": "Check",
  "row_name": null,
  "value": "0"
 },
 {
  "default_value": null,
  "doc_type": "User",
  "docstatus": 0,
  "doctype": "Property Setter",
  "doctype_or_field": "DocField",
  "field_name": "sb1",
  "is_system_generated": 0,
  "modified": "2024-03-06 18:53:30.392987",
  "module": "Akwad Frappe Fixes",
  "name": "User-sb1-depends_on",
  "property": "depends_on",
  "property_type": "Text",
  "row_name": null,
  "value": null
 },
 {
  "default_value": null,
  "doc_type": "User",
  "docstatus": 0,
  "doctype": "Property Setter",
  "doctype_or_field": "DocField",
  "field_name": "sb_allow_modules",
  "is_system_generated": 0,
  "modified": "2024-03-06 18:54:19.548047",
  "module": "Akwad Frappe Fixes",
  "name": "User-sb_allow_modules-depends_on",
  "property": "depends_on",
  "property_type": "Text",
  "row_name": null,
  "value": null
 },
 {
  "default_value": null,
  "doc_type": "Journal Entry",
  "docstatus": 0,
  "doctype": "Property Setter",
  "doctype_or_field": "DocType",
  "field_name": null,
  "is_system_generated": 0,
  "modified": "2024-04-17 23:46:09.086455",
  "module": "Akwad Frappe Fixes",
  "name": "Journal Entry-main-track_changes",
  "property": "track_changes",
  "property_type": "Check",
  "row_name": null,
  "value": "0"
 },
 {
  "default_value": null,
  "doc_type": "Salary Structure Assignment",
  "docstatus": 0,
  "doctype": "Property Setter",
  "doctype_or_field": "DocType",
  "field_name": null,
  "is_system_generated": 0,
  "modified": "2024-04-17 23:46:25.880113",
  "module": "Akwad Frappe Fixes",
  "name": "Salary Structure Assignment-main-track_changes",
  "property": "track_changes",
  "property_type": "Check",
  "row_name": null,
  "value": "0"
 },
 {
  "default_value": null,
  "doc_type": "Payment Entry",
  "docstatus": 0,
  "doctype": "Property Setter",
  "doctype_or_field": "DocType",
  "field_name": null,
  "is_system_generated": 0,
  "modified": "2024-04-17 23:46:42.722278",
  "module": "Akwad Frappe Fixes",
  "name": "Payment Entry-main-track_changes",
  "property": "track_changes",
  "property_type": "Check",
  "row_name": null,
  "value": "0"
 },
 {
  "default_value": null,
  "doc_type": "Stock Entry",
  "docstatus": 0,
  "doctype": "Property Setter",
  "doctype_or_field": "DocType",
  "field_name": null,
  "is_system_generated": 0,
  "modified": "2024-04-17 23:46:57.740250",
  "module": "Akwad Frappe Fixes",
  "name": "Stock Entry-main-track_changes",
  "property": "track_changes",
  "property_type": "Check",
  "row_name": null,
  "value": "0"
 },
 {
  "default_value": null,
  "doc_type": "Item",
  "docstatus": 0,
  "doctype": "Property Setter",
  "doctype_or_field": "DocType",
  "field_name": null,
  "is_system_generated": 0,
  "modified": "2024-04-17 23:47:09.568374",
  "module": "Akwad Frappe Fixes",
  "name": "Item-main-track_changes",
  "property": "track_changes",
  "property_type": "Check",
  "row_name": null,
  "value": "0"
 },
 {
  "default_value": null,
  "doc_type": "Employee Checkin",
  "docstatus": 0,
  "doctype": "Property Setter",
  "doctype_or_field": "DocType",
  "field_name": null,
  "is_system_generated": 0,
  "modified": "2024-04-17 23:47:16.282261",
  "module": "Akwad Frappe Fixes",
  "name": "Employee Checkin-main-track_changes",
  "property": "track_changes",
  "property_type": "Check",
  "row_name": null,
  "value": "0"
 },
 {
  "default_value": null,
  "doc_type": "Purchase Invoice",
  "docstatus": 0,
  "doctype": "Property Setter",
  "doctype_or_field": "DocType",
  "field_name": null,
  "is_system_generated": 0,
  "modified": "2024-04-17 23:48:05.590159",
  "module": "Akwad Frappe Fixes",
  "name": "Purchase Invoice-main-track_changes",
  "property": "track_changes",
  "property_type": "Check",
  "row_name": null,
  "value": "0"
 },
 {
  "default_value": null,
  "doc_type": "Sales Invoice",
  "docstatus": 0,
  "doctype": "Property Setter",
  "doctype_or_field": "DocType",
  "field_name": null,
  "is_system_generated": 0,
  "modified": "2024-04-17 23:48:12.571001",
  "module": "Akwad Frappe Fixes",
  "name": "Sales Invoice-main-track_changes",
  "property": "track_changes",
  "property_type": "Check",
  "row_name": null,
  "value": "0"
 },
 {
  "default_value": null,
  "doc_type": "Sales Order",
  "docstatus": 0,
  "doctype": "Property Setter",
  "doctype_or_field": "DocType",
  "field_name": null,
  "is_system_generated": 0,
  "modified": "2024-04-17 23:48:59.033927",
  "module": "Akwad Frappe Fixes",
  "name": "Sales Order-main-track_changes",
  "property": "track_changes",
  "property_type": "Check",
  "row_name": null,
  "value": "0"
 },
 {
  "default_value": null,
  "doc_type": "Purchase Order",
  "docstatus": 0,
  "doctype": "Property Setter",
  "doctype_or_field": "DocType",
  "field_name": null,
  "is_system_generated": 0,
  "modified": "2024-04-17 23:49:07.533752",
  "module": "Akwad Frappe Fixes",
  "name": "Purchase Order-main-track_changes",
  "property": "track_changes",
  "property_type": "Check",
  "row_name": null,
  "value": "0"
 },
 {
  "default_value": null,
  "doc_type": "Notification Settings",
  "docstatus": 0,
  "doctype": "Property Setter",
  "doctype_or_field": "DocType",
  "field_name": null,
  "is_system_generated": 0,
  "modified": "2024-04-17 23:50:41.780762",
  "module": "Akwad Frappe Fixes",
  "name": "Notification Settings-main-track_changes",
  "property": "track_changes",
  "property_type": "Check",
  "row_name": null,
  "value": "0"
 },
 {
  "default_value": null,
  "doc_type": "POS Invoice",
  "docstatus": 0,
  "doctype": "Property Setter",
  "doctype_or_field": "DocType",
  "field_name": null,
  "is_system_generated": 0,
  "modified": "2024-04-17 23:52:09.564345",
  "module": "Akwad Frappe Fixes",
  "name": "POS Invoice-main-track_changes",
  "property": "track_changes",
  "property_type": "Check",
  "row_name": null,
  "value": "0"
 }
]